{
	"name": "官方",
	"desc": "Flow 官方仓库",
	"addons": [
		{
			"id": "1",
			"name": "京东",
			"desc": "京东多合一签到",
			"icon": "https://raw.githubusercontent.com/un-bd/flow-sample/jd/icon.png",
			"url": "https://raw.githubusercontent.com/un-bd/flow-sample/jd/index.json",
			"version": "1.0.0"
		},
		{
			"id": "2",
			"name": "百度贴吧",
			"desc": "百度贴吧签到",
			"icon": "https://github.com/un-bd/flow-sample/jd/baidu.png",
			"url": "https://github.com/un-bd/flow-sample/jd/baidu.json",
			"version": "1.0.0"
		}
	]
}
